mdbub/__init__.py
mdbub/cli.py
mdbub/commands/__init__.py
mdbub/commands/about.py
mdbub/commands/export.py
mdbub/commands/print_kv.py
mdbub/commands/print_links.py
mdbub/commands/print_tags.py
mdbub/commands/quick.py
mdbub/commands/quickmode_config.py
mdbub/commands/tag_utils.py
mdbub/commands/version.py
mdbub/commands/view.py
mdbub/core/__init__.py
mdbub/core/mindmap.py
mdbub/core/mindmap_utils.py
mdbub/symbols.py
mdbub-0.4.0.dist-info/LICENSE
mdbub-0.4.0.dist-info/METADATA
mdbub-0.4.0.dist-info/WHEEL
mdbub-0.4.0.dist-info/entry_points.txt
mdbub-0.4.0.dist-info/RECORD
