Metadata-Version: 2.3
Name: mdbub
Version: 0.4.0
Summary: Terminal-first interactive mindmap CLI tool with extended markdown support
License: Apache-2.0
Keywords: cli,terminal,mindmap,markdown,productivity,tui
Author: dudash
Author-email: different.person@example.com
Requires-Python: >=3.9,<3.14
Classifier: Development Status :: 4 - Beta
Classifier: Environment :: Console
Classifier: Intended Audience :: Developers
Classifier: Intended Audience :: End Users/Desktop
Classifier: License :: OSI Approved :: Apache Software License
Classifier: Operating System :: OS Independent
Classifier: Programming Language :: Python :: 3
Classifier: Programming Language :: Python :: 3.9
Classifier: Programming Language :: Python :: 3.10
Classifier: Programming Language :: Python :: 3.11
Classifier: Programming Language :: Python :: 3.12
Classifier: Programming Language :: Python :: 3.13
Classifier: Topic :: Office/Business
Classifier: Topic :: Software Development :: Documentation
Classifier: Topic :: Text Processing :: Markup :: Markdown
Classifier: Topic :: Utilities
Requires-Dist: click (>=8.0.0,<8.2)
Requires-Dist: markdown (>=3.8,<4.0)
Requires-Dist: markdown-it-py (>=3.0.0,<4.0.0)
Requires-Dist: packaging (>=25.0,<26.0)
Requires-Dist: platformdirs (>=4.3.8,<5.0.0)
Requires-Dist: prompt-toolkit (>=3.0.51,<4.0.0)
Requires-Dist: pyyaml (>=6.0.2,<7.0.0)
Requires-Dist: requests (>=2.32.3,<3.0.0)
Requires-Dist: rich (>=14.0.0,<15.0.0)
Requires-Dist: rich-click (>=1.8.9,<2.0.0)
Requires-Dist: ruamel-yaml (>=0.18.10,<0.19.0)
Requires-Dist: toml (>=0.10,<0.11)
Requires-Dist: tomli (>=2.2.1,<3.0.0)
Requires-Dist: typer (>=0.15.4,<0.16.0)
Project-URL: Documentation, https://github.com/collabinator/mdbubbles/blob/main/README.md
Project-URL: Homepage, https://github.com/collabinator/mdbubbles
Project-URL: Repository, https://github.com/collabinator/mdbubbles
